JsonToXML/__init__.py
JsonToXML-0.0.2.dist-info/LICENSE.txt
JsonToXML-0.0.2.dist-info/METADATA
JsonToXML-0.0.2.dist-info/WHEEL
JsonToXML-0.0.2.dist-info/top_level.txt
JsonToXML-0.0.2.dist-info/RECORD
