Metadata-Version: 2.1
Name: JsonToXML
Version: 0.0.2
Summary: A Library to convert JSON into XML format.
Home-page: https://github.com/bhavyadeep-purswani/JsonTOXML
Author: Bhavyadeep Purswani
Author-email: bhavyadeep.purswani98@gmail.com
License: LICENCE.txt
Platform: UNKNOWN
Classifier: Programming Language :: Python :: 3
Classifier: Operating System :: OS Independent
